Metadata-Version: 2.4
Name: geocif
Version: 0.3.22
Summary: Models to visualize and forecast crop conditions and yields
Author-email: Ritvik Sahajpal <ritvik@umd.edu>
License: MIT
Project-URL: Homepage, https://ritviksahajpal.github.io/yield_forecasting/
Keywords: geocif
Classifier: Development Status :: 2 - Pre-Alpha
Classifier: Intended Audience :: Developers
Classifier: License :: OSI Approved :: MIT License
Classifier: Natural Language :: English
Classifier: Programming Language :: Python :: 3
Classifier: Programming Language :: Python :: 3.11
Classifier: Programming Language :: Python :: 3.12
Classifier: Programming Language :: Python :: 3.13
Requires-Python: >=3.11
License-File: LICENSE
Requires-Dist: boruta>=0.4.3
Requires-Dist: catboost>=1.2.8
Requires-Dist: fiona
Requires-Dist: gdal==3.11
Requires-Dist: pyeogpr>=2.4.7
Requires-Dist: pyproj
Requires-Dist: rasterio
Requires-Dist: rtree
Requires-Dist: shap>=0.48.0
Requires-Dist: shapely
Dynamic: license-file
